bottle_ocr_lib/__init__.py
bottle_ocr_lib/bottle_ocr.py
bottle_ocr_lib/cli.py
bottle_ocr_lib/auth/__init__.py
bottle_ocr_lib/auth/api_auth.py
bottle_ocr_lib/core/__init__.py
bottle_ocr_lib/core/ocr_processor.py
bottle_ocr_lib/core/prescription_extractor.py
bottle_ocr_lib/utils/__init__.py
bottle_ocr_lib/utils/config.py
bottle_ocr_lib/utils/exceptions.py
bottle_ocr_lib/utils/license_cache.py
bottle_ocr_lib/utils/validation.py
bottle_ocr_lib-1.0.2.dist-info/licenses/LICENSE
bottle_ocr_lib-1.0.2.dist-info/METADATA
bottle_ocr_lib-1.0.2.dist-info/WHEEL
bottle_ocr_lib-1.0.2.dist-info/entry_points.txt
bottle_ocr_lib-1.0.2.dist-info/top_level.txt
bottle_ocr_lib-1.0.2.dist-info/RECORD
