Metadata-Version: 2.4
Name: bottle-ocr-lib
Version: 1.0.2
Summary: Professional OCR and AI-powered prescription extraction library with secure license validation
Home-page: https://github.com/MichaelCrosson/bottle-ocr-lib
Author: Michael Crosson
Author-email: Michael Crosson <michael@bottleocr.com>
License: MIT
Project-URL: Homepage, https://github.com/MichaelCrosson/bottle-ocr-lib
Project-URL: Documentation, https://github.com/MichaelCrosson/bottle-ocr-lib#readme
Project-URL: Repository, https://github.com/MichaelCrosson/bottle-ocr-lib
Project-URL: Issues, https://github.com/MichaelCrosson/bottle-ocr-lib/issues
Keywords: ocr,prescription,ai,image-processing,healthcare,paddleocr,openai
Classifier: Development Status :: 5 - Production/Stable
Classifier: Intended Audience :: Developers
Classifier: Intended Audience :: Healthcare Industry
Classifier: License :: OSI Approved :: MIT License
Classifier: Operating System :: OS Independent
Classifier: Programming Language :: Python :: 3
Classifier: Programming Language :: Python :: 3.8
Classifier: Programming Language :: Python :: 3.9
Classifier: Programming Language :: Python :: 3.10
Classifier: Programming Language :: Python :: 3.11
Classifier: Programming Language :: Python :: 3.12
Classifier: Topic :: Scientific/Engineering :: Image Processing
Classifier: Topic :: Scientific/Engineering :: Artificial Intelligence
Classifier: Topic :: Software Development :: Libraries :: Python Modules
Requires-Python: >=3.8
License-File: LICENSE
Requires-Dist: requests>=2.25.0
Requires-Dist: pillow>=8.0.0
Requires-Dist: opencv-python>=4.5.0
Requires-Dist: numpy>=1.20.0
Requires-Dist: paddlepaddle>=2.4.0
Requires-Dist: paddleocr>=2.7.0
Requires-Dist: openai>=1.0.0
Requires-Dist: PyYAML>=5.4.0
Provides-Extra: dev
Requires-Dist: pytest>=6.0; extra == "dev"
Requires-Dist: pytest-cov>=2.10; extra == "dev"
Requires-Dist: black>=21.0; extra == "dev"
Requires-Dist: flake8>=3.8; extra == "dev"
Requires-Dist: mypy>=0.910; extra == "dev"
Dynamic: author
Dynamic: home-page
Dynamic: license-file
Dynamic: requires-python
